bridgex/NOTICE
bridgex/__init__.py
bridgex/__main__.py
bridgex/_bridgex.py
bridgex/OSL/LICENSE_MARKITDOWN
bridgex/OSL/LICENSE_PYSIDE6
bridgex/OSL/url_licenses.srm
bridgex/database/Manager.py
bridgex/database/__init__.py
bridgex/interface/__init__.py
bridgex/interface/_about.py
bridgex/interface/_initialHelp.py
bridgex/interface/_interface.py
bridgex/interface/_lang.py
bridgex/interface/_osl.py
bridgex/interface/resources_rc.py
bridgex/interface/ui_dialog_about.py
bridgex/interface/ui_dialog_language.py
bridgex/interface/ui_main_window.py
bridgex/interface/ui_osl.py
bridgex/interface/assets/img/gh-logo.png
bridgex/interface/assets/img/osl_icon.webp
bridgex/interface/assets/img/language/en_GB.svg
bridgex/interface/assets/img/language/es_CO.svg
bridgex/interface/assets/img/logo-bridgex/logo-bridgex-2.1.png
bridgex/interface/assets/img/logo-bridgex/logo-bridgex-2.2.png
bridgex/interface/assets/img/logo-bridgex/logo-bridgex-2.png
bridgex/interface/translations/locale/bridge_es_CO.qm
bridgex/interface/translations/locale/bridge_es_GB.qm
bridgex/interface/translations/others/ABOUT_en_GB.trg
bridgex/interface/translations/others/ABOUT_es_CO.trg
bridgex/interface/translations/others/IH_en_GB.srm
bridgex/interface/translations/others/IH_es_CO.srm
bridgex/interface/translations/others/NOTICE_en_GB.srm
bridgex/interface/translations/others/NOTICE_es_CO.srm
bridgex/logic/Converter.py
bridgex/logic/__init__.py
bridgex/logs/__init__.py
bridgex/models/Returning.py
bridgex/models/__init__.py
bridgex/utils/FilesManager.py
bridgex/utils/__init__.py
bridgex-0.1.0.dist-info/licenses/LICENSE
bridgex-0.1.0.dist-info/METADATA
bridgex-0.1.0.dist-info/WHEEL
bridgex-0.1.0.dist-info/entry_points.txt
bridgex-0.1.0.dist-info/top_level.txt
bridgex-0.1.0.dist-info/RECORD
