Metadata-Version: 2.4
Name: bridgex
Version: 0.1.0
Summary: Graphical interface for converting files to Markdown, built in Python and based on PySide6 and Markitdown.
Author-email: dev2forge <bridgex@dev2forge.software>
Maintainer-email: tutosrive <tutosrive@dev2forge.software>
License-Expression: MIT
Project-URL: Homepage, https://github.com/Dev2Forge/bridgex
Project-URL: Repository, https://github.com/Dev2Forge/bridgex
Project-URL: Issues, https://github.com/Dev2Forge/bridgex/issues
Keywords: markdown,converter,pyside6,gui,editor,viewer,pdf,docx,pptx,xls,xlsx,outlook,csv,txt,html,htm,file converter,markdown converter,markitdown,dev2forge,bridgex,microsoft office
Classifier: Development Status :: 4 - Beta
Classifier: Intended Audience :: End Users/Desktop
Classifier: Intended Audience :: Developers
Classifier: Topic :: Utilities
Classifier: Topic :: Text Processing :: Markup
Classifier: Programming Language :: Python :: 3.9
Classifier: Programming Language :: Python :: 3.10
Classifier: Programming Language :: Python :: 3.11
Classifier: Programming Language :: Python :: 3.12
Classifier: Programming Language :: Python :: 3.13
Classifier: Environment :: X11 Applications :: Qt
Classifier: Environment :: Win32 (MS Windows)
Classifier: Environment :: MacOS X
Requires-Python: <=3.13,>=3.9
License-File: LICENSE
Requires-Dist: markitdown[docx,outlook,pdf,pptx,xls,xlsx]==0.1.1
Requires-Dist: chromologger==0.1.8
Requires-Dist: PySide6-Essentials==6.9.0
Requires-Dist: sqlazo==0.1.5
Requires-Dist: chromolog==0.2.4
Dynamic: license-file
